bellameta/__init__.py
bellameta/base_metadata.py
bellameta/constants.py
bellameta/database.py
bellameta/types.py
bellameta/utils.py
bellameta-1.2.2.dist-info/licenses/LICENSE
bellameta-1.2.2.dist-info/METADATA
bellameta-1.2.2.dist-info/WHEEL
bellameta-1.2.2.dist-info/top_level.txt
bellameta-1.2.2.dist-info/RECORD
