Metadata-Version: 2.4
Name: bellameta
Version: 1.2.2
Summary: Metadata service for digital pathology WSI scans
Author-email: Paul Huettl <paulhuettl@web.de>
Maintainer-email: Paul Huettl <paulhuettl@web.de>, Lukas Wolfseher <lukas.wolfseher@informatik.uni-regensburg.de>
Project-URL: Source, https://github.com/spang-lab/bellameta
Classifier: Programming Language :: Python :: 3
Classifier: License :: OSI Approved :: MIT License
Classifier: Operating System :: OS Independent
Requires-Python: >=3.10
License-File: LICENSE
Requires-Dist: pandas>=2.0.0
Requires-Dist: pamly>=0.3.3
Requires-Dist: python-dotenv>=1.0.0
Requires-Dist: ruamel.yaml>=0.18.0
Dynamic: license-file
